STM32_ST_link/ST_Link.py
STM32_ST_link/__init__.py
STM32_ST_link/ST-LINK_USB_V2_1_Driver/dpinst_amd64.exe
STM32_ST_link/ST-LINK_USB_V2_1_Driver/dpinst_x86.exe
STM32_ST_link/ST-LINK_USB_V2_1_Driver/stlink_VCP.inf
STM32_ST_link/ST-LINK_USB_V2_1_Driver/stlink_dbg_winusb.inf
STM32_ST_link/ST-LINK_USB_V2_1_Driver/stlink_winusb_install.bat
STM32_ST_link/ST-LINK_USB_V2_1_Driver/stlinkdbgwinusb_x64.cat
STM32_ST_link/ST-LINK_USB_V2_1_Driver/stlinkdbgwinusb_x86.cat
STM32_ST_link/ST-LINK_USB_V2_1_Driver/stlinkvcp_x64.cat
STM32_ST_link/ST-LINK_USB_V2_1_Driver/stlinkvcp_x86.cat
STM32_ST_link/ST-LINK_USB_V2_1_Driver/amd64/WdfCoInstaller01009.dll
STM32_ST_link/ST-LINK_USB_V2_1_Driver/amd64/winusbcoinstaller2.dll
STM32_ST_link/ST-LINK_USB_V2_1_Driver/x86/WdfCoInstaller01009.dll
STM32_ST_link/ST-LINK_USB_V2_1_Driver/x86/winusbcoinstaller2.dll
STM32_ST_link/ST_Link_CLI/ST-LINK_CLI.exe
STM32_ST_link/ST_Link_CLI/ST-LinkUpgrade.exe
STM32_ST_link/ST_Link_CLI/STLinkUSBDriver.dll
STM32_ST_link/ST_Link_CLI/advapi32.dll
STM32_ST_link/ST_Link_CLI/comctl32.dll
STM32_ST_link/ST_Link_CLI/ExternalLoader/512W3A_STM3210E-EVAL.stldr
STM32_ST_link/ST_Link_CLI/ExternalLoader/IS42S32800G_STM32769I-EVAL.stldr
STM32_ST_link/ST_Link_CLI/ExternalLoader/IS61WV102416BLL_STM324x9I-EVAL.stldr
STM32_ST_link/ST_Link_CLI/ExternalLoader/IS61WV102416BLL_STM324xG-EVAL.stldr
STM32_ST_link/ST_Link_CLI/ExternalLoader/IS61WV102416BLL_STM32769I-EVAL.stldr
STM32_ST_link/ST_Link_CLI/ExternalLoader/IS61WV51216BLL_STM3210E-EVAL.stldr
STM32_ST_link/ST_Link_CLI/ExternalLoader/IS66WV51216EBLL_STM32723E-DISCO.stldr
STM32_ST_link/ST_Link_CLI/ExternalLoader/IS66WV51216EBLL_STM32F413H-DISCO.stldr
STM32_ST_link/ST_Link_CLI/ExternalLoader/M24LR-A_STM32303C-EVAL.stldr
STM32_ST_link/ST_Link_CLI/ExternalLoader/M24LR-A_STM32373C-EVAL.stldr
STM32_ST_link/ST_Link_CLI/ExternalLoader/M24LR-A_STM324x9I-EVAL.stldr
STM32_ST_link/ST_Link_CLI/ExternalLoader/M25P64_STM3210E-EVAL.stldr
STM32_ST_link-1.2.0.dist-info/METADATA
STM32_ST_link-1.2.0.dist-info/WHEEL
STM32_ST_link-1.2.0.dist-info/top_level.txt
STM32_ST_link-1.2.0.dist-info/RECORD
