Metadata-Version: 2.1
Name: STM32-ST-link
Version: 1.2.0
Summary: STM32 ST-Link CLI microcontroller operations: connect, program, and erase. Before use, STM32 ST-LINK Utility must be installed.
Home-page: https://github.com/Mason-mengze/STM32_ST-link
Author: Mason Zhou
Author-email: qq2087698086@gmail.com
Classifier: Programming Language :: Python :: 3
Classifier: License :: OSI Approved :: MIT License
Classifier: Operating System :: OS Independent
Requires-Python: >=3.8
